st_ant_statistic/__init__.py
st_ant_statistic/frontend/build/asset-manifest.json
st_ant_statistic/frontend/build/bootstrap.min.css
st_ant_statistic/frontend/build/index.html
st_ant_statistic/frontend/build/precache-manifest.2b45466acf4f65eefe9f04141ecc36b2.js
st_ant_statistic/frontend/build/precache-manifest.839d297490f0d5a02ec070a21f930d89.js
st_ant_statistic/frontend/build/precache-manifest.8c81e172ea72d8aee8672be482b6bbff.js
st_ant_statistic/frontend/build/precache-manifest.d4ee4a52545b54ba53a566b22654aed2.js
st_ant_statistic/frontend/build/service-worker.js
st_ant_statistic/frontend/build/static/js/2.26d1d8a0.chunk.js
st_ant_statistic/frontend/build/static/js/2.26d1d8a0.chunk.js.LICENSE.txt
st_ant_statistic/frontend/build/static/js/2.26d1d8a0.chunk.js.map
st_ant_statistic/frontend/build/static/js/2.7c06afa9.chunk.js
st_ant_statistic/frontend/build/static/js/2.7c06afa9.chunk.js.LICENSE.txt
st_ant_statistic/frontend/build/static/js/2.7c06afa9.chunk.js.map
st_ant_statistic/frontend/build/static/js/2.88a1d1f2.chunk.js
st_ant_statistic/frontend/build/static/js/2.88a1d1f2.chunk.js.LICENSE.txt
st_ant_statistic/frontend/build/static/js/2.88a1d1f2.chunk.js.map
st_ant_statistic/frontend/build/static/js/main.4af894cf.chunk.js
st_ant_statistic/frontend/build/static/js/main.4af894cf.chunk.js.map
st_ant_statistic/frontend/build/static/js/main.d1199d9b.chunk.js
st_ant_statistic/frontend/build/static/js/main.d1199d9b.chunk.js.map
st_ant_statistic/frontend/build/static/js/main.d7dba045.chunk.js
st_ant_statistic/frontend/build/static/js/main.d7dba045.chunk.js.map
st_ant_statistic/frontend/build/static/js/main.f525c3c1.chunk.js
st_ant_statistic/frontend/build/static/js/main.f525c3c1.chunk.js.map
st_ant_statistic/frontend/build/static/js/runtime-main.502c8693.js
st_ant_statistic/frontend/build/static/js/runtime-main.502c8693.js.map
st_ant_statistic-0.0.6.dist-info/LICENSE
st_ant_statistic-0.0.6.dist-info/METADATA
st_ant_statistic-0.0.6.dist-info/WHEEL
st_ant_statistic-0.0.6.dist-info/top_level.txt
st_ant_statistic-0.0.6.dist-info/RECORD
