Metadata-Version: 2.1
Name: st-ant-statistic
Version: 0.0.6
Summary: Streamlit Component for ANT Statistic
Author: 
Author-email: 
Requires-Python: >=3.6
License-File: LICENSE
Requires-Dist: streamlit (>=0.63)
